Workbook

Sheet Hierarchy
A1: Hierarchy for Procurements and Requisition
A2: Starts | B2: Category | C2: Employee | E2: HOD | F2: HR / Finance | G2: Procurement Committee Discussion | H2: Department | I2: Quotations | J2: Final Procurement Committee | K2: CEO | L2: Execution
A3: Requisition | B3: Stationary | C3: Initiate | E3: For Info | F3: — | G3: — | H3: Admin | I3: N/A | J3: — | K3: — | L3: Admin
A4: Requisition | B4: Vehicle Maintenance | C4: Initiate | E4: For Info | F4: — | G4: — | H4: Admin | I4: N/A | J4: — | K4: — | L4: Admin
A5: Requisition | B5: Vehicle Repair | C5: Initiate | E5: For Info | F5: — | G5: Review Technical & Financial Cost | H5: Admin | I5: Collect Quotation | J5: Review Technical & Financial Cost | K5: Approve | L5: Admin
A6: Requisition | B6: Other Repair & Maintenance | C6: Initiate | E6: For Info | F6: — | G6: Review Technical & Financial Cost | H6: Admin | I6: Collect Quotation | J6: If Required Material Repair & Maintenance | K6: Approve | L6: Admin
A7: Requisition | B7: Loan & Advance Salary | C7: Initiate | E7: Approval | F7: Approve up to 50k | G7: — | H7: Finance | I7: N/A | J7: — | K7: Approve above 50k | L7: Finance
A8: Requisition | B8: Event | C8: Initiate | E8: Approval | F8: — | G8: — | H8: Procurement Team | I8: Collect Quotations | J8: — | K8: Approve | L8: Procurement Team
A9: Requisition | B9: Specialized Projects | C9: Initiate | E9: — | F9: — | G9: Review Technical & Financial Cost | J9: Review Technical & Financial Cost | K9: Approve | L9: Procurement Team
A10: Requisition | B10: IT Equipments | C10: Initiate | E10: — | F10: — | G10: Review Technical & Financial Cost | H10: Procurement Team | I10: Collect Quotations | J10: Review Technical & Financial Cost | K10: Approve | L10: Procurement Team
A11: Requisition | B11: General Procurements Grocerry & Others | C11: Initiate | E11: — | F11: — | G11: Review Technical & Financial Cost | H11: Procurement Team | I11: Collect Quotations | J11: Review Technical & Financial Cost | K11: Approve | L11: Procurement Team
A12: Requisition | B12: General Procurements Electric Appliances | C12: Initiate | E12: — | F12: — | G12: Review Technical & Financial Cost | H12: Procurement Team | I12: Collect Quotations | J12: Review Technical & Financial Cost | K12: Approve | L12: Procurement Team
A13: Requisition | B13: Devices / Accessories | C13: Initiate | E13: — | F13: — | G13: Review Technical & Financial Cost | H13: Procurement Team | J13: Review Technical & Financial Cost | K13: Approve | L13: Procurement Team
A16: Footnotes
A18: *Loan eligibility based on last paid loan and employment tenure
A20: ** Loans up to PKR 50,000 require HR & CFO approval
A22: *** Each role must complete its action Max 24 working hours, minimum it will take 2 to 3 hours for execution

Sheet SOP
A1: Standard Operating Procedure (SOP)
A3: Procurement & Requisition Management
A5: 1. Purpose
A7: This SOP defines the standardized process for initiating, reviewing, approving, and executing procurement and requisition requests to ensure transparency, control, and timely processing across the organization.
A9: 2. Scope
A11: This SOP applies to all employees, departments, and management involved in requisition and procurement activities, including loans, advance salaries, events, IT equipment, devices, and general procurements.
A13: 3. Roles & Responsibilities
A15: Employee: Initiates requisition requests with complete justification.
A17: Head of Department (HOD): Reviews and initiates requests where applicable.
A19: Admin: Takes action on approved requisitions and coordinates documentation.
A21: HR / CFO: Reviews and approves financial matters (as per limits).
A23: Procurement Committee: Reviews technical and financial feasibility where required.
... A103: Review Cycle: Annual

Sheet REQ_CATEGORY
A1: CategoryID | B1: CategoryName
A2: 1 | B2: Stationary
A3: 2 | B3: Vehicle Maintenance
A4: 3 | B4: Vehicle Repair
A5: 4 | B5: Other Repair & Maintenance
A6: 5 | B6: Loan & Advance Salary
A7: 6 | B7: Event
A8: 7 | B8: Specialized Projects
A9: 8 | B9: IT Equipments
A10: 9 | B10: General Procurements - Grocery & Others
A11: 10 | B11: General Procurements - Electric Appliances
A12: 11 | B12: Devices / Accessories

Sheet Stationary
A1: ST_ID | B1: ST_Name
A2: 1 | B2: Pencil
A3: 2 | B3: Ball Point
A4: 3 | B4: Eraser
A5: 4 | B5: Shopner
A6: 5 | B6: Transparent Squash Tape (Thin)
A7: 6 | B7: Transparent Squash Tape (Thick)
A8: 7 | B8: Paper Tape
A9: 8 | B9: Carton Packing Tape
A10: 9 | B10: Paper Rims
A11: 10 | B11: Permenant Marker
A12: 11 | B12: Paper Tray
A13: 12 | B13: Stationery Stand
... A43: 42 | B43: Stamp Paper

Sheet IT Equipments
A1: IT_ID | B1: IT_Name
A2: 1 | B2: Desktop System
A3: 2 | B3: LCD Screen
A4: 3 | B4: Laptop
A5: 4 | B5: Keyboard
A6: 5 | B6: Mouse (Wired)
A7: 6 | B7: Mouse (Wire-Less)
A8: 7 | B8: VGA Cord
A9: 8 | B9: Power Cable
A10: 9 | B10: Printer
A11: 10 | B11: Copier
A12: 11 | B12: IP Phone
A13: 12 | B13: IP Phone Adaptor
... A39: 38 | B39: Head Phone

Sheet Generl PurchaseGrocery
A1: GPG_ID | B1: GPG_Name
A2: 1 | B2: Everyday Milk
A3: 2 | B3: Milk Pack
A4: 3 | B4: Tea Bag
A5: 4 | B5: Sugar
A6: 5 | B6: Air Freshener
A7: 6 | B7: Morten Spray
A8: 7 | B8: Scoth Brite
A9: 8 | B9: Lemon Max Dish Soap
A10: 9 | B10: Lemon Max Dish Liquid
A11: 10 | B11: Nestle Coffee
A12: 11 | B12: Duster
A13: 12 | B13: David Off Coffee
... A41: 40 | B41: Dry Mop Metal Rod

Sheet Generl Purchase Appliances
A1: GPA_ID | B1: GPA_Name
A2: 1 | B2: Air Conditioner Split 1 Ton
A3: 2 | B3: Air Conditioner Split 1.5 Ton
A4: 3 | B4: Air Conditioner Split 2 Ton
A5: 4 | B5: Water Dispenser
A6: 5 | B6: Refrigerator
A7: 6 | B7: Microwave Oven
A8: 7 | B8: Electric Kettle
A9: 8 | B9: Ceiling Fan
A10: 9 | B10: Projector
A11: 10 | B11: Video Conferencing System
A12: 11 | B12: CCTV System
A13: 12 | B13: Biometric Attendance Machine

Sheet REQ_ROLE
A1: RoleID | B1: RoleName
A2: 1 | B2: Employee
A3: 2 | B3: HOD
A4: 3 | B4: HR
A5: 4 | B5: Finance
A6: 5 | B6: Procurement Committee
A7: 6 | B7: Department Admin
A8: 7 | B8: Procurement Team
A9: 8 | B9: CEO
A10: 9 | B10: Execution Team

Sheet REQ_WORKFLOW
A1: WorkflowID | B1: CategoryID | C1: Category Name | D1: SequenceNo | E1: RoleID | F1: Role Name | G1: ActionName | H1: AmountFrom | I1: AmountTo | J1: IsMandatory
A2: 1 | B2: 1 | C2: =VLOOKUP(B2,REQ_CATEGORY!$A$1:$B$12,2,FALSE) -> Stationary | D2: 1 | E2: 1 | F2: =VLOOKUP(E2,REQ_ROLE!$A$1:$B$10,2,FALSE) -> Employee | G2: Initiate | H2: NULL | I2: NULL | J2: 1
A3: 2 | B3: 1 | C3: =VLOOKUP(B3,REQ_CATEGORY!$A$1:$B$12,2,FALSE) -> Stationary | D3: 2 | E3: 2 | F3: =VLOOKUP(E3,REQ_ROLE!$A$1:$B$10,2,FALSE) -> HOD | G3: For Information | H3: NULL | I3: NULL | J3: 1
A4: 3 | B4: 1 | C4: =VLOOKUP(B4,REQ_CATEGORY!$A$1:$B$12,2,FALSE) -> Stationary | D4: 3 | E4: 6 | F4: =VLOOKUP(E4,REQ_ROLE!$A$1:$B$10,2,FALSE) -> Department Admin | G4: Admin | H4: NULL | I4: NULL | J4: 1
A5: 4 | B5: 1 | C5: =VLOOKUP(B5,REQ_CATEGORY!$A$1:$B$12,2,FALSE) -> Stationary | D5: 4 | E5: 9 | F5: =VLOOKUP(E5,REQ_ROLE!$A$1:$B$10,2,FALSE) -> Execution Team | G5: Execute | H5: NULL | I5: NULL | J5: 1
A6: 5 | B6: 2 | C6: =VLOOKUP(B6,REQ_CATEGORY!$A$1:$B$12,2,FALSE) -> Vehicle Maintenance | D6: 1 | E6: 1 | F6: =VLOOKUP(E6,REQ_ROLE!$A$1:$B$10,2,FALSE) -> Employee | G6: Initiate | H6: NULL | I6: NULL | J6: 1
A7: 6 | B7: 2 | C7: =VLOOKUP(B7,REQ_CATEGORY!$A$1:$B$12,2,FALSE) -> Vehicle Maintenance | D7: 2 | E7: 2 | F7: =VLOOKUP(E7,REQ_ROLE!$A$1:$B$10,2,FALSE) -> HOD | G7: For Information | H7: NULL | I7: NULL | J7: 1
A8: 7 | B8: 2 | C8: =VLOOKUP(B8,REQ_CATEGORY!$A$1:$B$12,2,FALSE) -> Vehicle Maintenance | D8: 3 | E8: 6 | F8: =VLOOKUP(E8,REQ_ROLE!$A$1:$B$10,2,FALSE) -> Department Admin | G8: Admin | H8: NULL | I8: NULL | J8: 1
A9: 8 | B9: 2 | C9: =VLOOKUP(B9,REQ_CATEGORY!$A$1:$B$12,2,FALSE) -> Vehicle Maintenance | D9: 4 | E9: 9 | F9: =VLOOKUP(E9,REQ_ROLE!$A$1:$B$10,2,FALSE) -> Execution Team | G9: Execute | H9: NULL | I9: NULL | J9: 1
A10: 9 | B10: 3 | C10: =VLOOKUP(B10,REQ_CATEGORY!$A$1:$B$12,2,FALSE) -> Vehicle Repair | D10: 1 | E10: 1 | F10: =VLOOKUP(E10,REQ_ROLE!$A$1:$B$10,2,FALSE) -> Employee | G10: Initiate | H10: NULL | I10: NULL | J10: 1
A11: 10 | B11: 3 | C11: =VLOOKUP(B11,REQ_CATEGORY!$A$1:$B$12,2,FALSE) -> Vehicle Repair | D11: 2 | E11: 2 | F11: =VLOOKUP(E11,REQ_ROLE!$A$1:$B$10,2,FALSE) -> HOD | G11: For Information | H11: NULL | I11: NULL | J11: 1
A12: 11 | B12: 3 | C12: =VLOOKUP(B12,REQ_CATEGORY!$A$1:$B$12,2,FALSE) -> Vehicle Repair | D12: 3 | E12: 5 | F12: =VLOOKUP(E12,REQ_ROLE!$A$1:$B$10,2,FALSE) -> Procurement Committee | G12: Review Technical & Financial Cost | H12: NULL | I12: NULL | J12: 1
A13: 12 | B13: 3 | C13: =VLOOKUP(B13,REQ_CATEGORY!$A$1:$B$12,2,FALSE) -> Vehicle Repair | D13: 4 | E13: 6 | F13: =VLOOKUP(E13,REQ_ROLE!$A$1:$B$10,2,FALSE) -> Department Admin | G13: Admin | H13: NULL | I13: NULL | J13: 1
... A27: 26 | B27: 5 | C27: =VLOOKUP(B27,REQ_CATEGORY!$A$1:$B$12,2,FALSE) -> Loan & Advance Salary | D27: 2 | E27: 2 | F27: =VLOOKUP(E27,REQ_ROLE!$A$1:$B$10,2,FALSE) -> HOD | G27: Approve | H27: NULL | I27: NULL | J27: 1
A28: 27 | B28: 5 | C28: =VLOOKUP(B28,REQ_CATEGORY!$A$1:$B$12,2,FALSE) -> Loan & Advance Salary | D28: 3 | E28: 3 | F28: =VLOOKUP(E28,REQ_ROLE!$A$1:$B$10,2,FALSE) -> HR | G28: Approve | H28: 0 | I28: 50000 | J28: 1
A29: 28 | B29: 5 | C29: =VLOOKUP(B29,REQ_CATEGORY!$A$1:$B$12,2,FALSE) -> Loan & Advance Salary | D29: 4 | E29: 4 | F29: =VLOOKUP(E29,REQ_ROLE!$A$1:$B$10,2,FALSE) -> Finance | G29: Approve | H29: 0 | I29: 50000 | J29: 1
A30: 29 | B30: 5 | C30: =VLOOKUP(B30,REQ_CATEGORY!$A$1:$B$12,2,FALSE) -> Loan & Advance Salary | D30: 5 | E30: 8 | F30: =VLOOKUP(E30,REQ_ROLE!$A$1:$B$10,2,FALSE) -> CEO | G30: Approve | H30: 50001 | I30: NULL | J30: 1
A31: 30 | B31: 5 | C31: =VLOOKUP(B31,REQ_CATEGORY!$A$1:$B$12,2,FALSE) -> Loan & Advance Salary | D31: 6 | E31: 4 | F31: =VLOOKUP(E31,REQ_ROLE!$A$1:$B$10,2,FALSE) -> Finance | G31: Execute | H31: NULL | I31: NULL | J31: 1
A32: 31 | B32: 6 | C32: =VLOOKUP(B32,REQ_CATEGORY!$A$1:$B$12,2,FALSE) -> Event | D32: 1 | E32: 1 | F32: =VLOOKUP(E32,REQ_ROLE!$A$1:$B$10,2,FALSE) -> Employee | G32: Initiate | H32: NULL | I32: NULL | J32: 1
A33: 32 | B33: 6 | C33: =VLOOKUP(B33,REQ_CATEGORY!$A$1:$B$12,2,FALSE) -> Event | D33: 2 | E33: 2 | F33: =VLOOKUP(E33,REQ_ROLE!$A$1:$B$10,2,FALSE) -> HOD | G33: Approve | H33: NULL | I33: NULL | J33: 1
A34: 33 | B34: 6 | C34: =VLOOKUP(B34,REQ_CATEGORY!$A$1:$B$12,2,FALSE) -> Event | D34: 3 | E34: 7 | F34: =VLOOKUP(E34,REQ_ROLE!$A$1:$B$10,2,FALSE) -> Procurement Team | G34: Collect Quotations | H34: NULL | I34: NULL | J34: 1
A35: 34 | B35: 6 | C35: =VLOOKUP(B35,REQ_CATEGORY!$A$1:$B$12,2,FALSE) -> Event | D35: 4 | E35: 8 | F35: =VLOOKUP(E35,REQ_ROLE!$A$1:$B$10,2,FALSE) -> CEO | G35: Approve | H35: NULL | I35: NULL | J35: 1
A36: 35 | B36: 6 | C36: =VLOOKUP(B36,REQ_CATEGORY!$A$1:$B$12,2,FALSE) -> Event | D36: 5 | E36: 7 | F36: =VLOOKUP(E36,REQ_ROLE!$A$1:$B$10,2,FALSE) -> Procurement Team | G36: Execute | H36: NULL | I36: NULL | J36: 1
A37: 36 | B37: 7 | C37: =VLOOKUP(B37,REQ_CATEGORY!$A$1:$B$12,2,FALSE) -> Specialized Projects | D37: 1 | E37: 1 | F37: =VLOOKUP(E37,REQ_ROLE!$A$1:$B$10,2,FALSE) -> Employee | G37: Initiate | H37: NULL | I37: NULL | J37: 1
A38: 37 | B38: 7 | C38: =VLOOKUP(B38,REQ_CATEGORY!$A$1:$B$12,2,FALSE) -> Specialized Projects | D38: 2 | E38: 5 | F38: =VLOOKUP(E38,REQ_ROLE!$A$1:$B$10,2,FALSE) -> Procurement Committee | G38: Review Technical & Financial Cost | H38: NULL | I38: NULL | J38: 1
A39: 38 | B39: 7 | C39: =VLOOKUP(B39,REQ_CATEGORY!$A$1:$B$12,2,FALSE) -> Specialized Projects | D39: 3 | E39: 7 | F39: =VLOOKUP(E39,REQ_ROLE!$A$1:$B$10,2,FALSE) -> Procurement Team | G39: Collect Quotations | H39: NULL | I39: NULL | J39: 1
A40: 39 | B40: 7 | C40: =VLOOKUP(B40,REQ_CATEGORY!$A$1:$B$12,2,FALSE) -> Specialized Projects | D40: 4 | E40: 5 | F40: =VLOOKUP(E40,REQ_ROLE!$A$1:$B$10,2,FALSE) -> Procurement Committee | G40: Review Technical & Financial Cost | H40: NULL | I40: NULL | J40: 1
A41: 40 | B41: 7 | C41: =VLOOKUP(B41,REQ_CATEGORY!$A$1:$B$12,2,FALSE) -> Specialized Projects | D41: 5 | E41: 8 | F41: =VLOOKUP(E41,REQ_ROLE!$A$1:$B$10,2,FALSE) -> CEO | G41: Approve | H41: NULL | I41: NULL | J41: 1
A42: 41 | B42: 7 | C42: =VLOOKUP(B42,REQ_CATEGORY!$A$1:$B$12,2,FALSE) -> Specialized Projects | D42: 6 | E42: 7 | F42: =VLOOKUP(E42,REQ_ROLE!$A$1:$B$10,2,FALSE) -> Procurement Team | G42: Execute | H42: NULL | I42: NULL | J42: 1
... A66: 65 | B66: 11 | C66: =VLOOKUP(B66,REQ_CATEGORY!$A$1:$B$12,2,FALSE) -> Devices / Accessories | D66: 6 | E66: 7 | F66: =VLOOKUP(E66,REQ_ROLE!$A$1:$B$10,2,FALSE) -> Procurement Team | G66: Execute | H66: NULL | I66: NULL | J66: 1

Sheet EMP_REQUISITION
A1: ReqID | B1: EmployeeID | C1: CategoryID | E1: ReqAmount | F1: ReqPurpose | G1: Status | H1: CurrentSequence | I1: Sequence Name | J1: CreatedDate
A2: 1 | B2: 101 | C2: 1 | D2: =VLOOKUP(C2,REQ_CATEGORY!$A$1:$B$12,2,FALSE) -> Stationary | E2: 5000 | F2: Office stationary purchase | G2: Executed | H2: 4 | I2: =VLOOKUP(H2,REQ_WORKFLOW!$D$1:$G$66,3,FALSE) -> Execution Team | J2: 46011.621
A3: 2 | B3: 102 | C3: 2 | D3: =VLOOKUP(C3,REQ_CATEGORY!$A$1:$B$12,2,FALSE) -> Vehicle Maintenance | E3: 12000 | F3: Routine vehicle maintenance | G3: Executed | H3: 4 | I3: =VLOOKUP(H3,REQ_WORKFLOW!$D$1:$G$66,3,FALSE) -> Execution Team | J3: 46011.621
A4: 3 | B4: 103 | C4: 3 | D4: =VLOOKUP(C4,REQ_CATEGORY!$A$1:$B$12,2,FALSE) -> Vehicle Repair | E4: 85000 | F4: Engine repair | G4: Pending CEO Approval | H4: 7 | I4: =VLOOKUP(H4,REQ_WORKFLOW!$D$1:$G$66,3,FALSE) -> CEO | J4: 46011.621
A5: 4 | B5: 104 | C5: 4 | D5: =VLOOKUP(C5,REQ_CATEGORY!$A$1:$B$12,2,FALSE) -> Other Repair & Maintenance | E5: 45000 | F5: Office AC repair | G5: Under Committee Review | H5: 6 | I5: =VLOOKUP(H5,REQ_WORKFLOW!$D$1:$G$66,3,FALSE) -> Procurement Committee | J5: 46011.621
A6: 5 | B6: 105 | C6: 5 | D6: =VLOOKUP(C6,REQ_CATEGORY!$A$1:$B$12,2,FALSE) -> Loan & Advance Salary | E6: 40000 | F6: Personal loan | G6: Pending Finance Approval | H6: 4 | I6: =VLOOKUP(H6,REQ_WORKFLOW!$D$1:$G$66,3,FALSE) -> Execution Team | J6: 46011.621
A7: 6 | B7: 106 | C7: 5 | D7: =VLOOKUP(C7,REQ_CATEGORY!$A$1:$B$12,2,FALSE) -> Loan & Advance Salary | E7: 75000 | F7: Medical loan | G7: Pending CEO Approval | H7: 5 | I7: =VLOOKUP(H7,REQ_WORKFLOW!$D$1:$G$66,3,FALSE) -> Procurement Team | J7: 46011.621
A8: 7 | B8: 107 | C8: 6 | D8: =VLOOKUP(C8,REQ_CATEGORY!$A$1:$B$12,2,FALSE) -> Event | E8: 150000 | F8: Annual staff event | G8: Pending CEO Approval | H8: 4 | I8: =VLOOKUP(H8,REQ_WORKFLOW!$D$1:$G$66,3,FALSE) -> Execution Team | J8: 46011.621
A9: 8 | B9: 108 | C9: 7 | D9: =VLOOKUP(C9,REQ_CATEGORY!$A$1:$B$12,2,FALSE) -> Specialized Projects | E9: 500000 | F9: ERP customization | G9: Under Committee Review | H9: 4 | I9: =VLOOKUP(H9,REQ_WORKFLOW!$D$1:$G$66,3,FALSE) -> Execution Team | J9: 46011.621
A10: 9 | B10: 109 | C10: 8 | D10: =VLOOKUP(C10,REQ_CATEGORY!$A$1:$B$12,2,FALSE) -> IT Equipments | E10: 350000 | F10: Laptop purchase | G10: Quotation Collection | H10: 3 | I10: =VLOOKUP(H10,REQ_WORKFLOW!$D$1:$G$66,3,FALSE) -> Department Admin | J10: 46011.621
A11: 10 | B11: 110 | C11: 9 | D11: =VLOOKUP(C11,REQ_CATEGORY!$A$1:$B$12,2,FALSE) -> General Procurements - Grocery & Others | E11: 90000 | F11: Office groceries | G11: Quotation Collection | H11: 3 | I11: =VLOOKUP(H11,REQ_WORKFLOW!$D$1:$G$66,3,FALSE) -> Department Admin | J11: 46011.621
A12: 11 | B12: 111 | C12: 11 | D12: =VLOOKUP(C12,REQ_CATEGORY!$A$1:$B$12,2,FALSE) -> Devices / Accessories | E12: 25000 | F12: Barcode scanners | G12: Pending CEO Approval | H12: 5 | I12: =VLOOKUP(H12,REQ_WORKFLOW!$D$1:$G$66,3,FALSE) -> Procurement Team | J12: 46011.621

Sheet EMP_REQ_FLOW
A1: FlowID | B1: ReqID | C1: SequenceNo | D1: RoleID | E1: Role Name | F1: IsCompleted
A2: 1 | B2: 1 | C2: 1 | D2: 1 | E2: =VLOOKUP(D2,REQ_ROLE!$A$1:$B$10,2,FALSE) -> Employee | F2: 1
A3: 2 | B3: 1 | C3: 2 | D3: 2 | E3: =VLOOKUP(D3,REQ_ROLE!$A$1:$B$10,2,FALSE) -> HOD | F3: 1
A4: 3 | B4: 1 | C4: 3 | D4: 6 | E4: =VLOOKUP(D4,REQ_ROLE!$A$1:$B$10,2,FALSE) -> Department Admin | F4: 1
A5: 4 | B5: 1 | C5: 4 | D5: 9 | E5: =VLOOKUP(D5,REQ_ROLE!$A$1:$B$10,2,FALSE) -> Execution Team | F5: 1
A6: 5 | B6: 2 | C6: 1 | D6: 1 | E6: =VLOOKUP(D6,REQ_ROLE!$A$1:$B$10,2,FALSE) -> Employee | F6: 1
A7: 6 | B7: 2 | C7: 2 | D7: 2 | E7: =VLOOKUP(D7,REQ_ROLE!$A$1:$B$10,2,FALSE) -> HOD | F7: 1
A8: 7 | B8: 2 | C8: 3 | D8: 6 | E8: =VLOOKUP(D8,REQ_ROLE!$A$1:$B$10,2,FALSE) -> Department Admin | F8: 1
A9: 8 | B9: 2 | C9: 4 | D9: 9 | E9: =VLOOKUP(D9,REQ_ROLE!$A$1:$B$10,2,FALSE) -> Execution Team | F9: 1
A10: 9 | B10: 3 | C10: 1 | D10: 1 | E10: =VLOOKUP(D10,REQ_ROLE!$A$1:$B$10,2,FALSE) -> Employee | F10: 1
A11: 10 | B11: 3 | C11: 2 | D11: 2 | E11: =VLOOKUP(D11,REQ_ROLE!$A$1:$B$10,2,FALSE) -> HOD | F11: 1
A12: 11 | B12: 3 | C12: 3 | D12: 5 | E12: =VLOOKUP(D12,REQ_ROLE!$A$1:$B$10,2,FALSE) -> Procurement Committee | F12: 1
A13: 12 | B13: 3 | C13: 4 | D13: 6 | E13: =VLOOKUP(D13,REQ_ROLE!$A$1:$B$10,2,FALSE) -> Department Admin | F13: 1
... A66: 65 | B66: 11 | C66: 6 | D66: 7 | E66: =VLOOKUP(D66,REQ_ROLE!$A$1:$B$10,2,FALSE) -> Procurement Team | F66: 0

Sheet REQ_ACTION_LOG
A1: LogID | B1: ReqID | C1: RoleID | D1: Role Name | E1: ActionBy | F1: ActionTaken | G1: Remarks | H1: ActionDate
A2: 1 | B2: 1 | C2: 1 | D2: =VLOOKUP(C2,REQ_ROLE!$A$1:$B$10,2,FALSE) -> Employee | E2: 101 | F2: Initiated | G2: Request created | H2: 46011.622
A3: 2 | B3: 1 | C3: 2 | D3: =VLOOKUP(C3,REQ_ROLE!$A$1:$B$10,2,FALSE) -> HOD | E3: 201 | F3: Viewed | G3: HOD informed | H3: 46011.622
A4: 3 | B4: 1 | C4: 6 | D4: =VLOOKUP(C4,REQ_ROLE!$A$1:$B$10,2,FALSE) -> Department Admin | E4: 301 | F4: Processed | G4: Admin processed | H4: 46011.622
A5: 4 | B5: 1 | C5: 9 | D5: =VLOOKUP(C5,REQ_ROLE!$A$1:$B$10,2,FALSE) -> Execution Team | E5: 401 | F5: Executed | G5: Items issued | H5: 46011.622
A6: 5 | B6: 2 | C6: 1 | D6: =VLOOKUP(C6,REQ_ROLE!$A$1:$B$10,2,FALSE) -> Employee | E6: 102 | F6: Initiated | G6: Maintenance request | H6: 46011.622
A7: 6 | B7: 2 | C7: 2 | D7: =VLOOKUP(C7,REQ_ROLE!$A$1:$B$10,2,FALSE) -> HOD | E7: 202 | F7: Viewed | G7: HOD informed | H7: 46011.622
A8: 7 | B8: 2 | C8: 6 | D8: =VLOOKUP(C8,REQ_ROLE!$A$1:$B$10,2,FALSE) -> Department Admin | E8: 302 | F8: Processed | G8: Admin approved | H8: 46011.622
A9: 8 | B9: 2 | C9: 9 | D9: =VLOOKUP(C9,REQ_ROLE!$A$1:$B$10,2,FALSE) -> Execution Team | E9: 402 | F9: Executed | G9: Vehicle serviced | H9: 46011.622
A10: 9 | B10: 3 | C10: 1 | D10: =VLOOKUP(C10,REQ_ROLE!$A$1:$B$10,2,FALSE) -> Employee | E10: 103 | F10: Initiated | G10: Engine issue | H10: 46011.622
A11: 10 | B11: 3 | C11: 2 | D11: =VLOOKUP(C11,REQ_ROLE!$A$1:$B$10,2,FALSE) -> HOD | E11: 203 | F11: Viewed | G11: HOD informed | H11: 46011.622
A12: 11 | B12: 3 | C12: 5 | D12: =VLOOKUP(C12,REQ_ROLE!$A$1:$B$10,2,FALSE) -> Procurement Committee | E12: 501 | F12: Reviewed | G12: Estimated cost approved | H12: 46011.622
A13: 12 | B13: 3 | C13: 6 | D13: =VLOOKUP(C13,REQ_ROLE!$A$1:$B$10,2,FALSE) -> Department Admin | E13: 303 | F13: Processed | G13: Admin forwarded | H13: 46011.622
... A33: 32 | B33: 11 | C33: 8 | D33: =VLOOKUP(C33,REQ_ROLE!$A$1:$B$10,2,FALSE) -> CEO | E33: 801 | F33: Approved | G33: CEO approved | H33: 46011.622
